jykj/BusinessModel.py
jykj/__init__.py
jykj-1.0.0.dist-info/METADATA
jykj-1.0.0.dist-info/WHEEL
jykj-1.0.0.dist-info/top_level.txt
jykj-1.0.0.dist-info/RECORD
