Metadata-Version: 2.1
Name: jykj
Version: 1.0.0
Summary: Detects whether a person has entered a specified area.
Home-page: UNKNOWN
Author: shuairen
Author-email: renshuai@jylink.com
License: UNKNOWN
Platform: UNKNOWN
Classifier: Programming Language :: Python :: 3
Classifier: License :: OSI Approved :: MIT License
Classifier: Operating System :: OS Independent
